XStatic_D3-3.5.17.0-py2.7-nspkg.pth
XStatic_D3-3.5.17.0.dist-info/DESCRIPTION.rst
XStatic_D3-3.5.17.0.dist-info/METADATA
XStatic_D3-3.5.17.0.dist-info/RECORD
XStatic_D3-3.5.17.0.dist-info/WHEEL
XStatic_D3-3.5.17.0.dist-info/metadata.json
XStatic_D3-3.5.17.0.dist-info/namespace_packages.txt
XStatic_D3-3.5.17.0.dist-info/top_level.txt
xstatic/pkg/d3/__init__.py
xstatic/pkg/d3/data/d3.js
