Metadata-Version: 2.0
Name: XStatic-D3
Version: 3.5.17.0
Summary: D3 3.5.17 (XStatic packaging standard)
Home-page: http://d3js.org/
Author: Radomir Dopieralski
Author-email: openstack@sheep.art.pl
License: BSD
Keywords: d3 xstatic
Platform: any
